Metadata-Version: 1.1
Name: DatetimeRsys01
Version: 0.0.2
Summary: Python Library for DATE TIME finder from a String
Home-page: UNKNOWN
Author: Praveen Kumar Srivas
Author-email: pks101295nit2017@gmail.com
License: MIT
Keywords: date time
Platform: UNKNOWN
Classifier: Development Status :: 5 - Production/Stable
Classifier: Intended Audience :: Education
Classifier: Operating System :: Microsoft :: Windows :: Windows 10
Classifier: License :: OSI Approved :: MIT License
Classifier: Programming Language :: Python :: 3
